chatiq/__init__.py
chatiq/block_builders/__init__.py
chatiq/block_builders/channel_configuration.py
chatiq/block_builders/home_screen.py
chatiq/channel_info_parser.py
chatiq/chat_chain.py
chatiq/chatiq.py
chatiq/constants.py
chatiq/database.py
chatiq/document_loaders/__init__.py
chatiq/document_loaders/dummy_message.py
chatiq/document_loaders/message.py
chatiq/document_loaders/pdf.py
chatiq/document_loaders/plain_text.py
chatiq/document_loaders/slack_link.py
chatiq/document_loaders/unfurlink_link.py
chatiq/exceptions.py
chatiq/handlers/__init__.py
chatiq/handlers/app_home_opened.py
chatiq/handlers/app_mention.py
chatiq/handlers/app_uninstalled.py
chatiq/handlers/base.py
chatiq/handlers/channel_deleted.py
chatiq/handlers/context_save.py
chatiq/handlers/file_deleted.py
chatiq/handlers/file_shared.py
chatiq/handlers/message.py
chatiq/handlers/model_select.py
chatiq/handlers/temperature_select.py
chatiq/handlers/timezone_offset_select.py
chatiq/main.py
chatiq/models/__init__.py
chatiq/models/base.py
chatiq/models/slack_team.py
chatiq/prompt.py
chatiq/repositories/__init__.py
chatiq/repositories/slack_team_repository.py
chatiq/retriever.py
chatiq/settings.py
chatiq/text_processor.py
chatiq/utils.py
chatiq/vectorstore.py
chatiq-1.0.0.dist-info/LICENSE
chatiq-1.0.0.dist-info/METADATA
chatiq-1.0.0.dist-info/WHEEL
chatiq-1.0.0.dist-info/entry_points.txt
chatiq-1.0.0.dist-info/RECORD
