Metadata-Version: 2.1
Name: chatiq
Version: 1.0.0
Summary: A versatile Slack bot using GPT & Weaviate-powered long-term memory to accomplish various tasks.
Home-page: https://github.com/yujiosaka/ChatIQ
License: GPL-3.0
Author: yujiosaka
Author-email: yujisobe@gmail.com
Requires-Python: >=3.10,<3.11
Classifier: Development Status :: 3 - Alpha
Classifier: Intended Audience :: Developers
Classifier: License :: OSI Approved :: GNU General Public License v3 (GPLv3)
Classifier: Operating System :: OS Independent
Classifier: Programming Language :: Python :: 3
Classifier: Programming Language :: Python :: 3.10
Requires-Dist: beautifulsoup4 (>=4.12.2,<5.0.0)
Requires-Dist: cryptography (>=40.0.2,<41.0.0)
Requires-Dist: flask (>=2.3.2,<3.0.0)
Requires-Dist: gunicorn (>=20.1.0,<21.0.0)
Requires-Dist: langchain (>=0.0.173,<0.0.174)
Requires-Dist: openai (>=0.27.6,<0.28.0)
Requires-Dist: psycopg2-binary (>=2.9.6,<3.0.0)
Requires-Dist: pymupdf (>=1.22.3,<2.0.0)
Requires-Dist: python-dateutil (>=2.8.2,<3.0.0)
Requires-Dist: python-dotenv (>=1.0.0,<2.0.0)
Requires-Dist: pytz (>=2023.3,<2024.0)
Requires-Dist: requests (==2.28.0)
Requires-Dist: slack-bolt (>=1.18.0,<2.0.0)
Requires-Dist: slack-sdk (>=3.21.3,<4.0.0)
Requires-Dist: sqlalchemy (>=2.0.13,<3.0.0)
Requires-Dist: tiktoken (>=0.4.0,<0.5.0)
Requires-Dist: weaviate-client (>=3.17.1,<4.0.0)
Project-URL: Repository, https://github.com/yujiosaka/ChatIQ
